mcmc_statphys/__init__.py
mcmc_statphys/algorithm.py
mcmc_statphys/analysis.py
mcmc_statphys/cli.py
mcmc_statphys/draw.py
mcmc_statphys/mcmc_statphys.py
mcmc_statphys/method.py
mcmc_statphys/model.py
mcmc_statphys/algorithm/Anneal.py
mcmc_statphys/algorithm/Demon.py
mcmc_statphys/algorithm/HamiltonianMC.py
mcmc_statphys/algorithm/Kawasaki.py
mcmc_statphys/algorithm/Metropolis.py
mcmc_statphys/algorithm/Tempering.py
mcmc_statphys/algorithm/WangLandau.py
mcmc_statphys/algorithm/Wolff.py
mcmc_statphys/algorithm/__init__.py
mcmc_statphys/model/Heisenberg.py
mcmc_statphys/model/Ice.py
mcmc_statphys/model/Ising.py
mcmc_statphys/model/NVT.py
mcmc_statphys/model/Potts.py
mcmc_statphys/model/RFIsing.py
mcmc_statphys/model/SKmodel.py
mcmc_statphys/model/Staurss.py
mcmc_statphys/model/XY.py
mcmc_statphys/model/__init__.py
mcmc_statphys-1.0.0.dist-info/AUTHORS.rst
mcmc_statphys-1.0.0.dist-info/LICENSE
mcmc_statphys-1.0.0.dist-info/METADATA
mcmc_statphys-1.0.0.dist-info/WHEEL
mcmc_statphys-1.0.0.dist-info/entry_points.txt
mcmc_statphys-1.0.0.dist-info/top_level.txt
mcmc_statphys-1.0.0.dist-info/RECORD
