Metadata-Version: 2.1
Name: mcmc-statphys
Version: 1.0.0
Summary: A library project of Monte Carlo simulation algorithms for some statistical physics models (in particular, the Ising model and its variants).
Home-page: https://github.com/uynajgi/mcmc_statphys
Author: Uynaj GI
Author-email: suquan12148@outlook.com
License: MIT license
Keywords: mcmc_statphys
Platform: UNKNOWN
Classifier: Development Status :: 2 - Pre-Alpha
Classifier: Intended Audience :: Developers
Classifier: License :: OSI Approved :: MIT License
Classifier: Natural Language :: English
Classifier: Programming Language :: Python :: 3
Classifier: Programming Language :: Python :: 3.6
Classifier: Programming Language :: Python :: 3.7
Classifier: Programming Language :: Python :: 3.8
Requires-Python: >=3.6
License-File: LICENSE
License-File: AUTHORS.rst
Requires-Dist: Jinja2 (==3.1.2)
Requires-Dist: matplotlib (==3.7.0)
Requires-Dist: networkx (==2.8.4)
Requires-Dist: numpy (==1.23.5)
Requires-Dist: pandas (==1.5.3)
Requires-Dist: scipy (==1.10.0)
Requires-Dist: statsmodels (==0.13.5)
Requires-Dist: tqdm (==4.64.1)
Requires-Dist: animatplot (==0.4.2)
